static_log4shell/__init__.py
static_log4shell/scanner.py
static_log4shell-0.2.5.dist-info/METADATA
static_log4shell-0.2.5.dist-info/WHEEL
static_log4shell-0.2.5.dist-info/entry_points.txt
static_log4shell-0.2.5.dist-info/licenses/LICENSE
static_log4shell-0.2.5.dist-info/RECORD
