Metadata-Version: 2.4
Name: static-log4shell
Version: 0.2.5
Summary: Static analysis scanner for Log4Shell (CVE-2021-44228) vulnerabilities in Java projects
Project-URL: Homepage, https://github.com/username/static-log4shell
Project-URL: Documentation, https://github.com/username/static-log4shell#readme
Project-URL: Repository, https://github.com/username/static-log4shell.git
Project-URL: Bug Tracker, https://github.com/username/static-log4shell/issues
Project-URL: Changelog, https://github.com/username/static-log4shell/blob/main/CHANGELOG.md
Author-email: YourTeam <your-email@example.com>
License: MIT
License-File: LICENSE
Keywords: cve-2021-44228,java,log4j,log4shell,scanner,security,security-tools,static-analysis,vulnerability
Classifier: Development Status :: 4 - Beta
Classifier: Intended Audience :: Developers
Classifier: Intended Audience :: System Administrators
Classifier: License :: OSI Approved :: MIT License
Classifier: Operating System :: OS Independent
Classifier: Programming Language :: Python :: 3
Classifier: Programming Language :: Python :: 3.7
Classifier: Programming Language :: Python :: 3.8
Classifier: Programming Language :: Python :: 3.9
Classifier: Programming Language :: Python :: 3.10
Classifier: Programming Language :: Python :: 3.11
Classifier: Programming Language :: Python :: 3.12
Classifier: Topic :: Security
Classifier: Topic :: Software Development :: Quality Assurance
Classifier: Topic :: Software Development :: Testing
Requires-Python: >=3.7
Provides-Extra: dev
Requires-Dist: black>=21.0; extra == 'dev'
Requires-Dist: build>=0.7.0; extra == 'dev'
Requires-Dist: flake8>=3.8; extra == 'dev'
Requires-Dist: mypy>=0.800; extra == 'dev'
Requires-Dist: pytest-cov>=2.0; extra == 'dev'
Requires-Dist: pytest>=6.0; extra == 'dev'
Requires-Dist: twine>=3.4.0; extra == 'dev'
